[
  {
    "code": "00002",
    "lastName": "渡辺",
    "firstName": "和昌",
    "lastNameKana": "ワタナベ",
    "firstNameKana": "カズマサ",
    "abbr": "渡辺和昌",
    "status": "active"
  },
  {
    "code": "00003",
    "lastName": "赤沼",
    "firstName": "一広",
    "lastNameKana": "アカヌマ",
    "firstNameKana": "カズヒロ",
    "abbr": "赤沼一広",
    "status": "active"
  },
  {
    "code": "01001",
    "lastName": "丸山",
    "firstName": "美緒",
    "lastNameKana": "マルヤマ",
    "firstNameKana": "ミオ",
    "abbr": "丸山美緒",
    "status": "active"
  },
  {
    "code": "01002",
    "lastName": "伊東",
    "firstName": "奈津美",
    "lastNameKana": "イトウ",
    "firstNameKana": "ナツミ",
    "abbr": "伊東奈津美",
    "status": "active"
  },
  {
    "code": "02001",
    "lastName": "金子",
    "firstName": "真樹",
    "lastNameKana": "カネコ",
    "firstNameKana": "マサキ",
    "abbr": "金子真樹",
    "status": "active"
  },
  {
    "code": "02002",
    "lastName": "庭田",
    "firstName": "信夫",
    "lastNameKana": "ニワタ",
    "firstNameKana": "ノブオ",
    "abbr": "庭田信夫",
    "status": "active"
  },
  {
    "code": "02003",
    "lastName": "宮田",
    "firstName": "直明",
    "lastNameKana": "ミヤタ",
    "firstNameKana": "ナオアキ",
    "abbr": "宮田直明",
    "status": "expired"
  },
  {
    "code": "02004",
    "lastName": "海野",
    "firstName": "正士",
    "lastNameKana": "ウミノ",
    "firstNameKana": "タダシ",
    "abbr": "海野正士",
    "status": "active"
  },
  {
    "code": "02005",
    "lastName": "八木",
    "firstName": "良二",
    "lastNameKana": "ヤギ",
    "firstNameKana": "リョウジ",
    "abbr": "八木良二",
    "status": "expired"
  },
  {
    "code": "02006",
    "lastName": "加藤",
    "firstName": "昭伸",
    "lastNameKana": "カトウ",
    "firstNameKana": "アキノブ",
    "abbr": "加藤昭伸",
    "status": "active"
  },
  {
    "code": "02007",
    "lastName": "橋本",
    "firstName": "誠",
    "lastNameKana": "ハシモト",
    "firstNameKana": "マコト",
    "abbr": "橋本誠",
    "status": "expired"
  },
  {
    "code": "02008",
    "lastName": "浅野",
    "firstName": "良策",
    "lastNameKana": "アサノ",
    "firstNameKana": "リョウサク",
    "abbr": "浅野良策",
    "status": "expired"
  },
  {
    "code": "02009",
    "lastName": "赤沼",
    "firstName": "智子",
    "lastNameKana": "アカヌマ",
    "firstNameKana": "トモコ",
    "abbr": "赤沼智子",
    "status": "active"
  },
  {
    "code": "02010",
    "lastName": "椎名",
    "firstName": "純一",
    "lastNameKana": "シイナ",
    "firstNameKana": "ジュンイチ",
    "abbr": "椎名純一",
    "status": "expired"
  },
  {
    "code": "02011",
    "lastName": "秋葉",
    "firstName": "喜久男",
    "lastNameKana": "アキバ",
    "firstNameKana": "キクオ",
    "abbr": "秋葉喜久男",
    "status": "expired"
  },
  {
    "code": "02012",
    "lastName": "柴田",
    "firstName": "晋",
    "lastNameKana": "シバタ",
    "firstNameKana": "ススム",
    "abbr": "柴田晋",
    "status": "expired"
  },
  {
    "code": "02013",
    "lastName": "宮内",
    "firstName": "照美",
    "lastNameKana": "ミヤウチ",
    "firstNameKana": "テルミ",
    "abbr": "宮内照美",
    "status": "active"
  },
  {
    "code": "02014",
    "lastName": "近藤",
    "firstName": "駿介",
    "lastNameKana": "コンドウ",
    "firstNameKana": "シュンスケ",
    "abbr": "近藤駿介",
    "status": "expired"
  },
  {
    "code": "02015",
    "lastName": "大場",
    "firstName": "国浩",
    "lastNameKana": "オオバ",
    "firstNameKana": "クニヒロ",
    "abbr": "大場国浩",
    "status": "active"
  },
  {
    "code": "02016",
    "lastName": "石倉",
    "firstName": "雅彦",
    "lastNameKana": "イシクラ",
    "firstNameKana": "マサヒコ",
    "abbr": "石倉雅彦",
    "status": "expired"
  },
  {
    "code": "02017",
    "lastName": "奈良",
    "firstName": "光明",
    "lastNameKana": "ナラ",
    "firstNameKana": "ミツアキ",
    "abbr": "奈良光明",
    "status": "expired"
  },
  {
    "code": "02018",
    "lastName": "新岡",
    "firstName": "俊成",
    "lastNameKana": "ニイオカ",
    "firstNameKana": "トシナリ",
    "abbr": "新岡俊成",
    "status": "active"
  },
  {
    "code": "02019",
    "lastName": "小原",
    "firstName": "慶彰",
    "lastNameKana": "オバラ",
    "firstNameKana": "ヨシアキ",
    "abbr": "小原慶彰",
    "status": "expired"
  },
  {
    "code": "02020",
    "lastName": "平山",
    "firstName": "智大",
    "lastNameKana": "ヒラヤマ",
    "firstNameKana": "トモヒロ",
    "abbr": "平山智大",
    "status": "expired"
  },
  {
    "code": "02021",
    "lastName": "仁添",
    "firstName": "和昭",
    "lastNameKana": "ニゾエ",
    "firstNameKana": "カズアキ",
    "abbr": "仁添和昭",
    "status": "active"
  },
  {
    "code": "02022",
    "lastName": "栁田",
    "firstName": "至",
    "lastNameKana": "ヤナギダ",
    "firstNameKana": "イタル",
    "abbr": "栁田至",
    "status": "expired"
  },
  {
    "code": "02023",
    "lastName": "大野",
    "firstName": "幸男",
    "lastNameKana": "オオノ",
    "firstNameKana": "ユキオ",
    "abbr": "大野幸男",
    "status": "active"
  },
  {
    "code": "02024",
    "lastName": "柏",
    "firstName": "恭治",
    "lastNameKana": "カシワ",
    "firstNameKana": "キョウジ",
    "abbr": "柏恭治",
    "status": "expired"
  },
  {
    "code": "02025",
    "lastName": "脇田",
    "firstName": "俊明",
    "lastNameKana": "ワキタ",
    "firstNameKana": "トシアキ",
    "abbr": "脇田俊明",
    "status": "expired"
  },
  {
    "code": "02026",
    "lastName": "山中",
    "firstName": "裕希",
    "lastNameKana": "ヤマナカ",
    "firstNameKana": "ユウキ",
    "abbr": "山中裕希",
    "status": "expired"
  },
  {
    "code": "02027",
    "lastName": "直井",
    "firstName": "哲汰",
    "lastNameKana": "ナオイ",
    "firstNameKana": "テッタ",
    "abbr": "直井哲汰",
    "status": "expired"
  },
  {
    "code": "02028",
    "lastName": "坂本",
    "firstName": "誠",
    "lastNameKana": "サカモト",
    "firstNameKana": "マコト",
    "abbr": "坂本誠",
    "status": "expired"
  },
  {
    "code": "02029",
    "lastName": "杉本",
    "firstName": "博一",
    "lastNameKana": "スギモト",
    "firstNameKana": "ヒロカズ",
    "abbr": "杉本博一",
    "status": "expired"
  },
  {
    "code": "02030",
    "lastName": "大塚",
    "firstName": "良",
    "lastNameKana": "オオツカ",
    "firstNameKana": "リョウ",
    "abbr": "大塚良",
    "status": "expired"
  },
  {
    "code": "02031",
    "lastName": "巣山",
    "firstName": "昭雄",
    "lastNameKana": "スヤマ",
    "firstNameKana": "アキオ",
    "abbr": "巣山昭雄",
    "status": "expired"
  },
  {
    "code": "02032",
    "lastName": "前原",
    "firstName": "諭曇",
    "lastNameKana": "マエバラ",
    "firstNameKana": "ユクモ",
    "abbr": "前原諭曇",
    "status": "expired"
  },
  {
    "code": "02033",
    "lastName": "金",
    "firstName": "政亨",
    "lastNameKana": "キン",
    "firstNameKana": "マサユキ",
    "abbr": "金政亨",
    "status": "active"
  },
  {
    "code": "02034",
    "lastName": "千葉",
    "firstName": "正志",
    "lastNameKana": "チバ",
    "firstNameKana": "タダシ",
    "abbr": "千葉正志",
    "status": "expired"
  },
  {
    "code": "02035",
    "lastName": "小川",
    "firstName": "里沙",
    "lastNameKana": "オガワ",
    "firstNameKana": "リサ",
    "abbr": "小川里沙",
    "status": "active"
  },
  {
    "code": "02036",
    "lastName": "粟野",
    "firstName": "貞夫",
    "lastNameKana": "アワノ",
    "firstNameKana": "サダオ",
    "abbr": "粟野貞夫",
    "status": "active"
  },
  {
    "code": "02037",
    "lastName": "上村",
    "firstName": "美裕",
    "lastNameKana": "カミムラ",
    "firstNameKana": "ヨシヒロ",
    "abbr": "上村美裕",
    "status": "active"
  },
  {
    "code": "02038",
    "lastName": "服部",
    "firstName": "太郎",
    "lastNameKana": "ハットリ",
    "firstNameKana": "タロウ",
    "abbr": "服部太郎",
    "status": "expired"
  },
  {
    "code": "02039",
    "lastName": "影山",
    "firstName": "純一",
    "lastNameKana": "カゲヤマ",
    "firstNameKana": "ジュンイチ",
    "abbr": "影山純一",
    "status": "active"
  },
  {
    "code": "02040",
    "lastName": "佐藤",
    "firstName": "忍",
    "lastNameKana": "サトウ",
    "firstNameKana": "シノブ",
    "abbr": "佐藤忍",
    "status": "active"
  },
  {
    "code": "02041",
    "lastName": "安田",
    "firstName": "政弘",
    "lastNameKana": "ヤスダ",
    "firstNameKana": "マサヒロ",
    "abbr": "安田政弘",
    "status": "expired"
  },
  {
    "code": "02042",
    "lastName": "鷲頭",
    "firstName": "哲也",
    "lastNameKana": "ワシズ",
    "firstNameKana": "テツヤ",
    "abbr": "鷲頭哲也",
    "status": "active"
  },
  {
    "code": "02043",
    "lastName": "池田",
    "firstName": "玄海",
    "lastNameKana": "イケダ",
    "firstNameKana": "モトウミ",
    "abbr": "池田玄海",
    "status": "expired"
  },
  {
    "code": "02044",
    "lastName": "羽山",
    "firstName": "千鶴",
    "lastNameKana": "ハヤマ",
    "firstNameKana": "チヅル",
    "abbr": "羽山千鶴",
    "status": "expired"
  },
  {
    "code": "02045",
    "lastName": "石川",
    "firstName": "晃",
    "lastNameKana": "イシカワ",
    "firstNameKana": "アキラ",
    "abbr": "石川晃",
    "status": "active"
  },
  {
    "code": "02046",
    "lastName": "吉岡",
    "firstName": "優希",
    "lastNameKana": "ヨシオカ",
    "firstNameKana": "マサキ",
    "abbr": "吉岡優希",
    "status": "expired"
  },
  {
    "code": "02047",
    "lastName": "福與",
    "firstName": "宏紀",
    "lastNameKana": "フクヨ",
    "firstNameKana": "ヒロキ",
    "abbr": "福與宏紀",
    "status": "active"
  },
  {
    "code": "02048",
    "lastName": "佐藤",
    "firstName": "俊太",
    "lastNameKana": "サトウ",
    "firstNameKana": "シュンタ",
    "abbr": "佐藤俊太",
    "status": "expired"
  },
  {
    "code": "02049",
    "lastName": "米島",
    "firstName": "洋介",
    "lastNameKana": "ヨネシマ",
    "firstNameKana": "ヨウスケ",
    "abbr": "米島洋介",
    "status": "active"
  },
  {
    "code": "02050",
    "lastName": "内堀",
    "firstName": "秀哉",
    "lastNameKana": "ウチボリ",
    "firstNameKana": "シュウヤ",
    "abbr": "内堀秀哉",
    "status": "expired"
  },
  {
    "code": "02051",
    "lastName": "手塚",
    "firstName": "博紀",
    "lastNameKana": "テヅカ",
    "firstNameKana": "ヒロキ",
    "abbr": "手塚博紀",
    "status": "active"
  },
  {
    "code": "02052",
    "lastName": "森原",
    "firstName": "義之",
    "lastNameKana": "モリハラ",
    "firstNameKana": "ヨシユキ",
    "abbr": "森原義之",
    "status": "active"
  },
  {
    "code": "02053",
    "lastName": "ミョウ",
    "firstName": "タウン",
    "lastNameKana": "ミョウ",
    "firstNameKana": "タウン",
    "abbr": "ミョウタウ",
    "status": "expired"
  },
  {
    "code": "02054",
    "lastName": "ピャイ ソン",
    "firstName": "アウン",
    "lastNameKana": "ピャイソン",
    "firstNameKana": "アウン",
    "abbr": "ピャイ ソ",
    "status": "expired"
  },
  {
    "code": "02055",
    "lastName": "田澤",
    "firstName": "三晴",
    "lastNameKana": "タザワ",
    "firstNameKana": "ミツハル",
    "abbr": "田澤三晴",
    "status": "active"
  },
  {
    "code": "02056",
    "lastName": "稲垣",
    "firstName": "一徳",
    "lastNameKana": "イナガキ",
    "firstNameKana": "カズノリ",
    "abbr": "稲垣一徳",
    "status": "active"
  },
  {
    "code": "02057",
    "lastName": "小島",
    "firstName": "正彦",
    "lastNameKana": "コジマ",
    "firstNameKana": "マサヒコ",
    "abbr": "小島正彦",
    "status": "active"
  },
  {
    "code": "02058",
    "lastName": "阿部",
    "firstName": "幸夫",
    "lastNameKana": "アベ",
    "firstNameKana": "サチオ",
    "abbr": "阿部幸夫",
    "status": "active"
  },
  {
    "code": "02059",
    "lastName": "川邨",
    "firstName": "宣佳",
    "lastNameKana": "カワムラ",
    "firstNameKana": "ノブヨシ",
    "abbr": "川邨宣佳",
    "status": "expired"
  },
  {
    "code": "02060",
    "lastName": "今田",
    "firstName": "義美",
    "lastNameKana": "コンタ",
    "firstNameKana": "ヨシミ",
    "abbr": "今田義美",
    "status": "active"
  },
  {
    "code": "02061",
    "lastName": "鈴木",
    "firstName": "晃義",
    "lastNameKana": "スズキ",
    "firstNameKana": "テルヨシ",
    "abbr": "鈴木晃義",
    "status": "active"
  },
  {
    "code": "02062",
    "lastName": "萩川",
    "firstName": "義則",
    "lastNameKana": "ハギカワ",
    "firstNameKana": "ヨシノリ",
    "abbr": "萩川義則",
    "status": "expired"
  },
  {
    "code": "02070",
    "lastName": "SRIVASTAVA",
    "firstName": "ABHINAV",
    "lastNameKana": "スリバスタヴァ",
    "firstNameKana": "アビナフ",
    "abbr": "SRIVA",
    "status": "expired"
  },
  {
    "code": "02071",
    "lastName": "NASANBAYAR",
    "firstName": "GANBAT",
    "lastNameKana": "ナサンバヤル",
    "firstNameKana": "ガンバト",
    "abbr": "NASAN",
    "status": "active"
  },
  {
    "code": "02072",
    "lastName": "RAJIB",
    "firstName": "NURUL AL",
    "lastNameKana": "ラジブ",
    "firstNameKana": "ヌールル アル",
    "abbr": "RAJIB",
    "status": "active"
  },
  {
    "code": "02063",
    "lastName": "髙柳",
    "firstName": "知之",
    "lastNameKana": "タカヤナギ",
    "firstNameKana": "トモユキ",
    "abbr": "髙柳知之",
    "status": "active"
  },
  {
    "code": "02064",
    "lastName": "小井𡈽",
    "firstName": "孝一",
    "lastNameKana": "コイド",
    "firstNameKana": "コウイチ",
    "abbr": "小井𡈽孝",
    "status": "expired"
  },
  {
    "code": "02065",
    "lastName": "小林",
    "firstName": "英治",
    "lastNameKana": "コバヤシ",
    "firstNameKana": "エイジ",
    "abbr": "小林英治",
    "status": "expired"
  },
  {
    "code": "02066",
    "lastName": "北田",
    "firstName": "純",
    "lastNameKana": "キタダ",
    "firstNameKana": "ジュン",
    "abbr": "北田純",
    "status": "expired"
  },
  {
    "code": "02067",
    "lastName": "竹内",
    "firstName": "徹",
    "lastNameKana": "タケウチ",
    "firstNameKana": "トオル",
    "abbr": "竹内徹",
    "status": "expired"
  },
  {
    "code": "02068",
    "lastName": "伊藤",
    "firstName": "啄也",
    "lastNameKana": "イトウ",
    "firstNameKana": "タクヤ",
    "abbr": "伊藤啄也",
    "status": "expired"
  },
  {
    "code": "02069",
    "lastName": "新井",
    "firstName": "穂高",
    "lastNameKana": "アライ",
    "firstNameKana": "ホダカ",
    "abbr": "新井穂高",
    "status": "expired"
  }
]
